{
    "msedge-stable-win7and8-x86": {
        "\u6587\u4ef6\u540d": "MicrosoftEdge_X86_109.0.1518.140.exe",
        "\u4e0b\u8f7d\u94fe\u63a5": "https://msedge.sb.tlu.dl.delivery.mp.microsoft.com/filestreamingservice/files/d87a3bbd-7fe5-4ec3-b806-293cca78b363?P1=1714241565&P2=404&P3=2&P4=XamXUT%2bExMijJFUvBRfRn%2fKmufKSUdttt84HJUgWCYAB4IK4fUuFCZT5LHj%2fj9mgfkUwg%2bUg2lctrVuq%2f2tp4A%3d%3d",
        "\u5b57\u8282\u5927\u5c0f": 128512968,
        "Sha1": "TzGshrNvfT5B7bCaZaS/OYA8rro=",
        "Sha256": "2b48ce3b304b7b9a8f9377a42d8661ecdc53c5f2c6ee708da9d62127c7802c18",
        "version": "109.0.1518.140"
    },
    "msedge-stable-win7and8-x64": {
        "\u6587\u4ef6\u540d": "MicrosoftEdge_X64_109.0.1518.140.exe",
        "\u4e0b\u8f7d\u94fe\u63a5": "https://msedge.sb.tlu.dl.delivery.mp.microsoft.com/filestreamingservice/files/0c4084f3-1bed-4246-b8ed-206ccbe60e3c?P1=1714241565&P2=404&P3=2&P4=kjXbtBVNz6Zpv4D0hLtvxaXZuOdP0CDzosggH6yd8W%2fnmfqnbZ2e8Zjy%2fAyAcabySC%2flS42QAgSkrmOPoBKdig%3d%3d",
        "\u5b57\u8282\u5927\u5c0f": 140696008,
        "Sha1": "ZAErwtGciZxGa0c/GYSACHDsL9o=",
        "Sha256": "70d496873a0a1ca14ae0a038d25856b2121b1b4b7bad9801ce639b144bac41f8",
        "version": "109.0.1518.140"
    },
    "msedge-stable-win7and8-ARM64": {
        "\u6587\u4ef6\u540d": "MicrosoftEdge_ARM64_109.0.1518.140.exe",
        "\u4e0b\u8f7d\u94fe\u63a5": "https://msedge.sb.tlu.dl.delivery.mp.microsoft.com/filestreamingservice/files/630083c1-24b5-4545-9b0b-0f35a727bf89?P1=1714241566&P2=404&P3=2&P4=ClBHiAPr2mTh8KbyzFZAmKMK8OKpH5HRQhaVUAxmDdeKYyiMSjVygHLQxFIP%2bq7rGi%2b0QsPoMbibyFFZVxWeFA%3d%3d",
        "\u5b57\u8282\u5927\u5c0f": 138498616,
        "Sha1": "7MODObKWCcJNgJHj75dHDyYxr7E=",
        "Sha256": "5de04fdc41cdbac64cecc86a3fd24ddba1520c6b7e04dbd1bfd9d3a6ec7bb971",
        "version": "109.0.1518.140"
    },
    "msedge-stable-win-x86": {
        "\u6587\u4ef6\u540d": "MicrosoftEdge_X86_124.0.2478.51.exe",
        "\u4e0b\u8f7d\u94fe\u63a5": "https://msedge.sb.tlu.dl.delivery.mp.microsoft.com/filestreamingservice/files/c72378bf-b773-4976-875d-8f5846714303?P1=1714241565&P2=404&P3=2&P4=hpW%2fn20xs%2fEHCcElJJJCM7EeiyQocFTYvLv4BhO9O%2bR8FOukd49P8NPKT3RAw3%2b%2bG1cw0fk0a%2bYrRCRi%2bBRZ3A%3d%3d",
        "\u5b57\u8282\u5927\u5c0f": 156330440,
        "Sha1": "++3v/xwqYJwz5yKlh92ax4S7KfM=",
        "Sha256": "af7400e4a7ef6968aef56ed41ffe5a4381abcda87a8930102ef6d1e879e514f0",
        "version": "124.0.2478.51"
    },
    "msedge-stable-win-x64": {
        "\u6587\u4ef6\u540d": "MicrosoftEdge_X64_124.0.2478.51.exe",
        "\u4e0b\u8f7d\u94fe\u63a5": "https://msedge.sb.tlu.dl.delivery.mp.microsoft.com/filestreamingservice/files/edfb651f-a66d-4d43-a53e-37c78eea9a16?P1=1714241565&P2=404&P3=2&P4=jw6KyvbTT21nh76BMI8qEHnsfUPQWovo0m3%2f6uQJ3gvyPOany94GPAv2FVWozAhIHqYdsJdgYMebpFluJNED8A%3d%3d",
        "\u5b57\u8282\u5927\u5c0f": 172682808,
        "Sha1": "Vowrymifv4cKlly0hnp2ovVUn90=",
        "Sha256": "92f8f1114c969dde4b8819de90c6b0662e9183c733e1378a64375fe4051382a4",
        "version": "124.0.2478.51"
    },
    "msedge-stable-win-ARM64": {
        "\u6587\u4ef6\u540d": "MicrosoftEdge_ARM64_124.0.2478.51.exe",
        "\u4e0b\u8f7d\u94fe\u63a5": "https://msedge.sb.tlu.dl.delivery.mp.microsoft.com/filestreamingservice/files/b3a4c74d-59fe-4714-8738-08185a0966d4?P1=1714241565&P2=404&P3=2&P4=e%2bY9JqBRWTT%2fmjp18Js3qBMxIqC1Bu%2fOuxgQ%2fihWKHVr%2bUUUDytrqsY4Yfp07d6HeZoEXBh%2fIFO6RJi9Z4oDpA%3d%3d",
        "\u5b57\u8282\u5927\u5c0f": 168427064,
        "Sha1": "0mcL0Dpj55xkAT3IEuXcp3z7FEY=",
        "Sha256": "d8b08dc30cd1d0cf89df389c8588a6256e0764c5bd903cae1fd62740826a400b",
        "version": "124.0.2478.51"
    },
    "msedge-beta-win-x86": {
        "\u6587\u4ef6\u540d": "MicrosoftEdge_X86_124.0.2478.51.exe",
        "\u4e0b\u8f7d\u94fe\u63a5": "https://msedge.sb.tlu.dl.delivery.mp.microsoft.com/filestreamingservice/files/c72378bf-b773-4976-875d-8f5846714303?P1=1714241566&P2=404&P3=2&P4=JxYRVRFbY5wYy2XoJ%2fgejrMNEkTPUzfFVekJEotHj%2fJRm2aOYQFikDIi%2bRQktkpnQPro6VeZ6bqFwD%2bGyFy9lQ%3d%3d",
        "\u5b57\u8282\u5927\u5c0f": 156330440,
        "Sha1": "++3v/xwqYJwz5yKlh92ax4S7KfM=",
        "Sha256": "af7400e4a7ef6968aef56ed41ffe5a4381abcda87a8930102ef6d1e879e514f0",
        "version": "124.0.2478.51"
    },
    "msedge-beta-win-x64": {
        "\u6587\u4ef6\u540d": "MicrosoftEdge_X64_124.0.2478.51.exe",
        "\u4e0b\u8f7d\u94fe\u63a5": "https://msedge.sb.tlu.dl.delivery.mp.microsoft.com/filestreamingservice/files/edfb651f-a66d-4d43-a53e-37c78eea9a16?P1=1714241566&P2=404&P3=2&P4=Sf5G2iXNSkfxlwneUbQdJzW65jJ3UCukHe0fH24Il1LIpQaD8NYN4UQ4JRE1p9DxhQUPAwYocwU7vXNJw9vWZA%3d%3d",
        "\u5b57\u8282\u5927\u5c0f": 172682808,
        "Sha1": "Vowrymifv4cKlly0hnp2ovVUn90=",
        "Sha256": "92f8f1114c969dde4b8819de90c6b0662e9183c733e1378a64375fe4051382a4",
        "version": "124.0.2478.51"
    },
    "msedge-beta-win-ARM64": {
        "\u6587\u4ef6\u540d": "MicrosoftEdge_ARM64_124.0.2478.51.exe",
        "\u4e0b\u8f7d\u94fe\u63a5": "https://msedge.sb.tlu.dl.delivery.mp.microsoft.com/filestreamingservice/files/b3a4c74d-59fe-4714-8738-08185a0966d4?P1=1714241566&P2=404&P3=2&P4=B6OjsTQgeWCsV0R6oFZuyZY8EZOZPLsT1M4kAyVLy4hRjg1L15%2bUZw3ybkHKcrXZvQPMRAVbRPf0eiYYu%2f1iAg%3d%3d",
        "\u5b57\u8282\u5927\u5c0f": 168427064,
        "Sha1": "0mcL0Dpj55xkAT3IEuXcp3z7FEY=",
        "Sha256": "d8b08dc30cd1d0cf89df389c8588a6256e0764c5bd903cae1fd62740826a400b",
        "version": "124.0.2478.51"
    },
    "msedge-dev-win-x86": {
        "\u6587\u4ef6\u540d": "MicrosoftEdge_X86_125.0.2518.0.exe",
        "\u4e0b\u8f7d\u94fe\u63a5": "https://msedge.sb.tlu.dl.delivery.mp.microsoft.com/filestreamingservice/files/4711a3fb-ca0b-452e-b331-df64a705edfc?P1=1714241566&P2=404&P3=2&P4=lofdbhb0ALQpqjtG%2fctWqURCuRVWd4Ejgu6DzhgNUU6q1D692aOyF6RW%2fpDwdtfLYM1wyiUrY6Wic8y%2fLGYLEw%3d%3d",
        "\u5b57\u8282\u5927\u5c0f": 156530232,
        "Sha1": "onCWruChYxyiG/3FIAFNghot6GY=",
        "Sha256": "026c33f8b5bae6082d277e888521631881640a19566d85a6f44ed8a27d6e2461",
        "version": "125.0.2518.0"
    },
    "msedge-dev-win-x64": {
        "\u6587\u4ef6\u540d": "MicrosoftEdge_X64_125.0.2518.0.exe",
        "\u4e0b\u8f7d\u94fe\u63a5": "https://msedge.sb.tlu.dl.delivery.mp.microsoft.com/filestreamingservice/files/c3092bf0-e9b6-45a6-a8c8-689d33d7d51e?P1=1714241567&P2=404&P3=2&P4=BsvhZG0yUcP8sbsrhimKsTNJM55JN4BfyYYZNRl%2fwxtT9lSfN%2b1Ye1OXqJoeuZ1e3ut1rtBpz2VZUBLT5HySNg%3d%3d",
        "\u5b57\u8282\u5927\u5c0f": 172928048,
        "Sha1": "Briu6GY4xs+WkoYIgIlOStQasOY=",
        "Sha256": "c372f4557d3ece1662c47db4c7d88f39ac97f10e418e6c7cf87b805e83944cc3",
        "version": "125.0.2518.0"
    },
    "msedge-dev-win-ARM64": {
        "\u6587\u4ef6\u540d": "MicrosoftEdge_ARM64_125.0.2518.0.exe",
        "\u4e0b\u8f7d\u94fe\u63a5": "https://msedge.sb.tlu.dl.delivery.mp.microsoft.com/filestreamingservice/files/6298f2fa-14e0-499a-ae1d-4e5a433c930c?P1=1714241567&P2=404&P3=2&P4=T4fZRU740GRJ41gN7%2bbGOeDdF20hhGHAmgB0OZdaW7SHAT%2b8wlqC%2bCyXjFKzB5aCTChjyIVy5d14MoHs5iFnjQ%3d%3d",
        "\u5b57\u8282\u5927\u5c0f": 169024560,
        "Sha1": "mJz2P399Yw14d4OQWUtaWahkDUE=",
        "Sha256": "7e9eadb695a31023da34ae488562e091e20352ce4f7ac4d8ffd1fcb68c984f1e",
        "version": "125.0.2518.0"
    },
    "msedge-canary-win-x86": {
        "\u6587\u4ef6\u540d": "MicrosoftEdge_X86_126.0.2536.0.exe",
        "\u4e0b\u8f7d\u94fe\u63a5": "https://msedge.sb.tlu.dl.delivery.mp.microsoft.com/filestreamingservice/files/1f14da60-15f3-48a1-9fa5-6cb4549e4b0d?P1=1714241567&P2=404&P3=2&P4=I52iapGI2VGO4mjDOBoTCBT8C5gQ37GnZP1aAfUSJYE0%2blWPuulJxOJbgGe8%2f820dLV4dSyPC%2fsIG30deCy5UA%3d%3d",
        "\u5b57\u8282\u5927\u5c0f": 156868152,
        "Sha1": "qjja/b9xewFThvxJHG4A19XZqMk=",
        "Sha256": "6d53a431e70df8ec81ae7b5597972d5a428ea04901f37d012af348f5a606664a",
        "version": "126.0.2536.0"
    },
    "msedge-canary-win-x64": {
        "\u6587\u4ef6\u540d": "MicrosoftEdge_X64_126.0.2536.0.exe",
        "\u4e0b\u8f7d\u94fe\u63a5": "https://msedge.sb.tlu.dl.delivery.mp.microsoft.com/filestreamingservice/files/bdab1197-aa53-4781-818f-6c775979ef35?P1=1714241567&P2=404&P3=2&P4=bx9n4oIjuxAiA%2bXV7U21LYNSLvkXLajsvaHBl1gWGOWMpZC4Wirb2T%2fJWwd0G2bKeCE8ByYjI5cgAw2e6B5ljw%3d%3d",
        "\u5b57\u8282\u5927\u5c0f": 172401720,
        "Sha1": "WKaZ/jp5gZGvjtYc1KvJG4RfA9A=",
        "Sha256": "1f9b3cd7c6b930b6ceb2ffba1e79d2724c210cafbc8ce06999a3e22eca3e8110",
        "version": "126.0.2536.0"
    },
    "msedge-canary-win-ARM64": {
        "\u6587\u4ef6\u540d": "MicrosoftEdge_ARM64_126.0.2536.0.exe",
        "\u4e0b\u8f7d\u94fe\u63a5": "https://msedge.sb.tlu.dl.delivery.mp.microsoft.com/filestreamingservice/files/f4a1e0d8-def0-4310-896b-52b10bbe5e41?P1=1714241568&P2=404&P3=2&P4=c1s0UelFmWmJU%2bJaqrWrnN%2f1CMjRDf47qcb2f2O0cNRW3zk7wID3v1SVG%2fVlo0c6otdzYI%2fD5KwUTNO6zFaO6Q%3d%3d",
        "\u5b57\u8282\u5927\u5c0f": 169337800,
        "Sha1": "Am9bJPV6McYltqvGPj7u2pqe0go=",
        "Sha256": "08d4a63361300572984723ab8bd5bfec360adead88602a29d59f90a5f516b739",
        "version": "126.0.2536.0"
    }
}