{
    "msedge-stable-win7and8-x86": {
        "\u6587\u4ef6\u540d": "MicrosoftEdge_X86_109.0.1518.140.exe",
        "\u4e0b\u8f7d\u94fe\u63a5": "https://msedge.sb.tlu.dl.delivery.mp.microsoft.com/filestreamingservice/files/d87a3bbd-7fe5-4ec3-b806-293cca78b363?P1=1720527544&P2=404&P3=2&P4=iFozapwPbZ9ohJ%2fg9OmbXux9Zt3KBV5V%2bZjaYjCALsUMgx9aqTBrtf4BVOYgLva1J6J%2fRf7e4c9iDJ9BZV%2b9NQ%3d%3d",
        "\u5b57\u8282\u5927\u5c0f": 128512968,
        "Sha1": "TzGshrNvfT5B7bCaZaS/OYA8rro=",
        "Sha256": "2b48ce3b304b7b9a8f9377a42d8661ecdc53c5f2c6ee708da9d62127c7802c18",
        "version": "109.0.1518.140"
    },
    "msedge-stable-win7and8-x64": {
        "\u6587\u4ef6\u540d": "MicrosoftEdge_X64_109.0.1518.140.exe",
        "\u4e0b\u8f7d\u94fe\u63a5": "https://msedge.sb.tlu.dl.delivery.mp.microsoft.com/filestreamingservice/files/0c4084f3-1bed-4246-b8ed-206ccbe60e3c?P1=1720527545&P2=404&P3=2&P4=SdJx%2b%2fWM2m%2fLslgauDHtiClIT3lxVRb3OPeWi3roA%2bwd24k5x6fpQsmfmrSGpB6mG1WGH2pgKF5IUPa%2bB8jMOA%3d%3d",
        "\u5b57\u8282\u5927\u5c0f": 140696008,
        "Sha1": "ZAErwtGciZxGa0c/GYSACHDsL9o=",
        "Sha256": "70d496873a0a1ca14ae0a038d25856b2121b1b4b7bad9801ce639b144bac41f8",
        "version": "109.0.1518.140"
    },
    "msedge-stable-win7and8-ARM64": {
        "\u6587\u4ef6\u540d": "MicrosoftEdge_ARM64_109.0.1518.140.exe",
        "\u4e0b\u8f7d\u94fe\u63a5": "https://msedge.sb.tlu.dl.delivery.mp.microsoft.com/filestreamingservice/files/630083c1-24b5-4545-9b0b-0f35a727bf89?P1=1720527545&P2=404&P3=2&P4=nC%2f2eHYMYGRPkG6p%2f9ybffa%2bczq0HNyWL%2b1VYgNG4N44SV8rE1Ac0b5XnYtxEGqqaSEi29VDQpEhwwxASk6WPQ%3d%3d",
        "\u5b57\u8282\u5927\u5c0f": 138498616,
        "Sha1": "7MODObKWCcJNgJHj75dHDyYxr7E=",
        "Sha256": "5de04fdc41cdbac64cecc86a3fd24ddba1520c6b7e04dbd1bfd9d3a6ec7bb971",
        "version": "109.0.1518.140"
    },
    "msedge-stable-win-x86": {
        "\u6587\u4ef6\u540d": "MicrosoftEdge_X86_126.0.2592.81.exe",
        "\u4e0b\u8f7d\u94fe\u63a5": "https://msedge.sb.tlu.dl.delivery.mp.microsoft.com/filestreamingservice/files/fe10d5ce-7e15-4adc-a28c-6cea33fb9f51?P1=1720527544&P2=404&P3=2&P4=Ss%2blUF%2fZVKrlo6lAIrAXjrcqibpQQmBJ6EY7dx02m7uL%2b9NWXI9kRdO0q5Gwe3sYG7OHXeg0vSJ8bcbQUMPpSQ%3d%3d",
        "\u5b57\u8282\u5927\u5c0f": 156551632,
        "Sha1": "twIegz77fVC857NS5195xVStBeE=",
        "Sha256": "a1d10b601f738147463050306841847ae30daca4244fb5beb34f32fbc7c38111",
        "version": "126.0.2592.81"
    },
    "msedge-stable-win-x64": {
        "\u6587\u4ef6\u540d": "MicrosoftEdge_X64_126.0.2592.81.exe",
        "\u4e0b\u8f7d\u94fe\u63a5": "https://msedge.sb.tlu.dl.delivery.mp.microsoft.com/filestreamingservice/files/1110bf63-c6ce-4714-969b-b3028b441c47?P1=1720527544&P2=404&P3=2&P4=CI5sfgTXIeQCN1T5ovE%2fmgnt7NmGXnLV7CDwk%2b3FlGkj5murf8hOU%2flogKpXa%2fM%2bJuKSCf%2fFmBbb4e6HuBI9Jw%3d%3d",
        "\u5b57\u8282\u5927\u5c0f": 173082168,
        "Sha1": "cyL3g/Us7pk2UqV0mguyCJlqCbc=",
        "Sha256": "ef3d57108d03c7f59bce637aa4843867a3977a564ee34d685bf264b0796936b8",
        "version": "126.0.2592.81"
    },
    "msedge-stable-win-ARM64": {
        "\u6587\u4ef6\u540d": "MicrosoftEdge_ARM64_126.0.2592.81.exe",
        "\u4e0b\u8f7d\u94fe\u63a5": "https://msedge.sb.tlu.dl.delivery.mp.microsoft.com/filestreamingservice/files/eeeaf621-906c-492f-8e53-e9bd681dca93?P1=1720527544&P2=404&P3=2&P4=Rur4uZ1L5CHmPhryzffnzoz99v47EPU3ST2a8wLblduwEu5gI2Pej2dhJ6KcRcPPgdg%2bmuL6W2cQD3ZTWsvmgQ%3d%3d",
        "\u5b57\u8282\u5927\u5c0f": 173776456,
        "Sha1": "WhbLUSVGwUEq2H29pf2ylYnPbPk=",
        "Sha256": "ed913e0982f166f2ed8a26bd78f01346dd825978386ea7fb469e4ccf482aa38a",
        "version": "126.0.2592.81"
    },
    "msedge-beta-win-x86": {
        "\u6587\u4ef6\u540d": "MicrosoftEdge_X86_127.0.2651.15.exe",
        "\u4e0b\u8f7d\u94fe\u63a5": "https://msedge.sb.tlu.dl.delivery.mp.microsoft.com/filestreamingservice/files/efbd3edd-c509-4661-93b7-12925b8bc4f3?P1=1720527545&P2=404&P3=2&P4=howMlnlrMt2x%2byHGC4qql4PG3WJswDttTDblgc%2fRz94KcttdqTfK%2b%2fi%2f%2bZG4A9cDcznKdkBKO9F1ppPBol%2fGGw%3d%3d",
        "\u5b57\u8282\u5927\u5c0f": 155834424,
        "Sha1": "nE6ylkZ/ue/sCmdgBqIY809zoAE=",
        "Sha256": "0270f41712f2f1160539eb270fe9e032ddb6fc6ed4b52447eb6edd2c8d6e38b2",
        "version": "127.0.2651.15"
    },
    "msedge-beta-win-x64": {
        "\u6587\u4ef6\u540d": "MicrosoftEdge_X64_127.0.2651.15.exe",
        "\u4e0b\u8f7d\u94fe\u63a5": "https://msedge.sb.tlu.dl.delivery.mp.microsoft.com/filestreamingservice/files/26c34b5f-6bc3-400e-897e-1a62e1ebffce?P1=1720527545&P2=404&P3=2&P4=DbT4o7HFZlNARno91QAXQbYVeEVlox40LGTXMURqp8rsupLkhJguWtWDXIn50bXyWruqN6u4rZ7IXAiU9t9H0A%3d%3d",
        "\u5b57\u8282\u5927\u5c0f": 172430392,
        "Sha1": "dYAu77em3uq8Tz0cWBAMKxCWimE=",
        "Sha256": "40651a56fa0cb48d5db0520ff2441dde7cc3dabb0da37c24a22284abbc557ab5",
        "version": "127.0.2651.15"
    },
    "msedge-beta-win-ARM64": {
        "\u6587\u4ef6\u540d": "MicrosoftEdge_ARM64_127.0.2651.15.exe",
        "\u4e0b\u8f7d\u94fe\u63a5": "https://msedge.sb.tlu.dl.delivery.mp.microsoft.com/filestreamingservice/files/0c4ae9b8-407b-433f-a144-afe691648427?P1=1720527546&P2=404&P3=2&P4=CiuygLuxYXp%2bRRbNVtgNckHWTzVOxe2Z9pocsQxU6cgoCUBsBmwDfjI9hJQgQ%2fijFa61mazjn%2f8%2f1qd%2by8uZFQ%3d%3d",
        "\u5b57\u8282\u5927\u5c0f": 173229112,
        "Sha1": "uPZtZ0fvT//7aeLD1ekX7FsQsaM=",
        "Sha256": "3b34e9f2b18405a62411a157dbf9854cfa860c5d93b0963e8eebd5b2a46cc0ea",
        "version": "127.0.2651.15"
    },
    "msedge-dev-win-x86": {
        "\u6587\u4ef6\u540d": "MicrosoftEdge_X86_128.0.2661.0.exe",
        "\u4e0b\u8f7d\u94fe\u63a5": "https://msedge.sb.tlu.dl.delivery.mp.microsoft.com/filestreamingservice/files/04d0e2d7-aa28-449a-915b-5315d6f72801?P1=1720527546&P2=404&P3=2&P4=KU0zwbuTdRZkKIMn1gXUypz2%2fwrHrLe5Ou2c%2bbIcxVSuZpwKEScBK6fXMdETIZ4r9O1iBfxI5x2E3MHuGqV9uQ%3d%3d",
        "\u5b57\u8282\u5927\u5c0f": 156031032,
        "Sha1": "8zNjnHFTd9xv6Dr5BR51wo2uaZU=",
        "Sha256": "bb996dfe3a8243eef049532573f12d9c6e5c1f7de70eb5618fc5ba2a087460c5",
        "version": "128.0.2661.0"
    },
    "msedge-dev-win-x64": {
        "\u6587\u4ef6\u540d": "MicrosoftEdge_X64_128.0.2661.0.exe",
        "\u4e0b\u8f7d\u94fe\u63a5": "https://msedge.sb.tlu.dl.delivery.mp.microsoft.com/filestreamingservice/files/828bf0b7-f6d8-4dc6-8584-9bf70ec311bd?P1=1720527546&P2=404&P3=2&P4=Esmy8X4U4RuvAT0A7l%2f28alvWz9HBJbWhIfeStgNM9h6p7N7psYFmbiNC1tme1qdTOyRohj90Mi%2bHwiFX25GhQ%3d%3d",
        "\u5b57\u8282\u5927\u5c0f": 172537304,
        "Sha1": "pCtaog0UppjAr5G+9nyKsHn7zUg=",
        "Sha256": "b548a093d9cd58b8efef351ca7f8774e3dc18b36f12c09f70f0c0df2339a7f49",
        "version": "128.0.2661.0"
    },
    "msedge-dev-win-ARM64": {
        "\u6587\u4ef6\u540d": "MicrosoftEdge_ARM64_128.0.2661.0.exe",
        "\u4e0b\u8f7d\u94fe\u63a5": "https://msedge.sb.tlu.dl.delivery.mp.microsoft.com/filestreamingservice/files/65075457-0fe9-4a18-b9d3-fa7431523372?P1=1720527546&P2=404&P3=2&P4=O%2fiuSvaQT6ifkSvRSutyAM98SnnLWfnsP0WSDlIqiHQpd4wLDkC7xosdWIlM7upiqtP09vmiuJdoqB0tGquH7g%3d%3d",
        "\u5b57\u8282\u5927\u5c0f": 173434840,
        "Sha1": "Msj5xmIgwgpR6GTERefHK84OCKE=",
        "Sha256": "1ba6b705f25ac0a92af18ace994b69be9c89fde5df79bde54161633e52ff8a03",
        "version": "128.0.2661.0"
    },
    "msedge-canary-win-x86": {
        "\u6587\u4ef6\u540d": "MicrosoftEdge_X86_128.0.2685.0.exe",
        "\u4e0b\u8f7d\u94fe\u63a5": "https://msedge.sb.tlu.dl.delivery.mp.microsoft.com/filestreamingservice/files/2e549913-0153-4190-8338-14fafb5e6780?P1=1720527547&P2=404&P3=2&P4=Sxa1Dh9N19KIRRtltMDXmG5PW24C5AnbHnXQsHCLoTnxPBQPXfsc3KiZQPdYkQRr09ECa8KbQyApeZW1wy2gqQ%3d%3d",
        "\u5b57\u8282\u5927\u5c0f": 156145096,
        "Sha1": "3BNDJH0LcGJtB7IJUxhpKMU2yRs=",
        "Sha256": "c2a427962032bea4a33a2d23773888a78c700c74b5adf03abc3c9c34124c83ba",
        "version": "128.0.2685.0"
    },
    "msedge-canary-win-x64": {
        "\u6587\u4ef6\u540d": "MicrosoftEdge_X64_128.0.2685.0.exe",
        "\u4e0b\u8f7d\u94fe\u63a5": "https://msedge.sb.tlu.dl.delivery.mp.microsoft.com/filestreamingservice/files/b785dded-3d30-4e01-9a17-6af881383fb1?P1=1720527547&P2=404&P3=2&P4=GZl7FoVyBmKXOricOjoZ7ByAOfMctoEfkYZNXSwHXRHvHTw5oLYPu%2fObLAmU7RlMqhpD4fhDh1YDF%2fDD7pGuCg%3d%3d",
        "\u5b57\u8282\u5927\u5c0f": 172511288,
        "Sha1": "/jV5IOPQIgdQ1Sz43+F0SOXuiVk=",
        "Sha256": "579cc50e3ce9bde8c2f3dcea33122159e156b4044933fb53f16ad0710eb986da",
        "version": "128.0.2685.0"
    },
    "msedge-canary-win-ARM64": {
        "\u6587\u4ef6\u540d": "MicrosoftEdge_ARM64_128.0.2685.0.exe",
        "\u4e0b\u8f7d\u94fe\u63a5": "https://msedge.sb.tlu.dl.delivery.mp.microsoft.com/filestreamingservice/files/dca0178e-5220-4b89-b10a-f58d34deb833?P1=1720527547&P2=404&P3=2&P4=GJpLQvXBiyTHIgIeDPN8bSMuOQ6Fjpwgwn6htSXd8hPy7RC3i3pxJnL%2fyiMyuPRnZMvBDCHILR743WZdYKVtTw%3d%3d",
        "\u5b57\u8282\u5927\u5c0f": 173384248,
        "Sha1": "PTHv+HoJqxIjMGKmkRBuWk4Grwc=",
        "Sha256": "36ca1c341095dd5766ef7e3ee6fae1ab26c47d7584f2023a01481663648b817e",
        "version": "128.0.2685.0"
    }
}