{
    "msedge-stable-win7and8-x86": {
        "\u6587\u4ef6\u540d": "MicrosoftEdge_X86_109.0.1518.140.exe",
        "\u4e0b\u8f7d\u94fe\u63a5": "https://msedge.sb.tlu.dl.delivery.mp.microsoft.com/filestreamingservice/files/d87a3bbd-7fe5-4ec3-b806-293cca78b363?P1=1770167780&P2=404&P3=2&P4=krzjGCYNlUuBNxGQdBdO4GsMG3qyce3%2fFHzmmhmKtUt4eeZl9NMv1%2f8tB%2bJ01Um2ooxNbxlsN3fjPro4DjTdiQ%3d%3d",
        "\u5b57\u8282\u5927\u5c0f": 128512968,
        "Sha1": "TzGshrNvfT5B7bCaZaS/OYA8rro=",
        "Sha256": "2b48ce3b304b7b9a8f9377a42d8661ecdc53c5f2c6ee708da9d62127c7802c18",
        "version": "109.0.1518.140"
    },
    "msedge-stable-win7and8-x64": {
        "\u6587\u4ef6\u540d": "MicrosoftEdge_X64_109.0.1518.140.exe",
        "\u4e0b\u8f7d\u94fe\u63a5": "https://msedge.sb.tlu.dl.delivery.mp.microsoft.com/filestreamingservice/files/0c4084f3-1bed-4246-b8ed-206ccbe60e3c?P1=1770167780&P2=404&P3=2&P4=DIu1yLenNOBet6b3JuJDoBkzIls0d33thbKPC%2bAKdja5bUPf%2fRlrnCXkrZ0kzpPaSZAtlOzIyUsMChkF2mPjEQ%3d%3d",
        "\u5b57\u8282\u5927\u5c0f": 140696008,
        "Sha1": "ZAErwtGciZxGa0c/GYSACHDsL9o=",
        "Sha256": "70d496873a0a1ca14ae0a038d25856b2121b1b4b7bad9801ce639b144bac41f8",
        "version": "109.0.1518.140"
    },
    "msedge-stable-win7and8-ARM64": {
        "\u6587\u4ef6\u540d": "MicrosoftEdge_ARM64_109.0.1518.140.exe",
        "\u4e0b\u8f7d\u94fe\u63a5": "https://msedge.sb.tlu.dl.delivery.mp.microsoft.com/filestreamingservice/files/630083c1-24b5-4545-9b0b-0f35a727bf89?P1=1770167780&P2=404&P3=2&P4=QKeDQQ6GQ6YXeu5XCeIe7hZlbKd9WkfVNhxEfyo5NbV6%2bqf%2bKnElHVU%2bcq5vhsw2JQofRuCE%2bhi1mWZS7ER6UQ%3d%3d",
        "\u5b57\u8282\u5927\u5c0f": 138498616,
        "Sha1": "7MODObKWCcJNgJHj75dHDyYxr7E=",
        "Sha256": "5de04fdc41cdbac64cecc86a3fd24ddba1520c6b7e04dbd1bfd9d3a6ec7bb971",
        "version": "109.0.1518.140"
    },
    "msedge-stable-win-x86": {
        "\u6587\u4ef6\u540d": "MicrosoftEdge_X86_144.0.3719.92.exe",
        "\u4e0b\u8f7d\u94fe\u63a5": "https://msedge.sb.tlu.dl.delivery.mp.microsoft.com/filestreamingservice/files/e77d46aa-24fc-496c-8a5f-0870d564a6d4?P1=1770167780&P2=404&P3=2&P4=PzJQ%2fCDgUr8ibNodFOGXdah6qAW6OwuCk3kWVKWti4p2oOiHOhqo4KpRwYnRNPD8dPmyW6P%2bHuo1zeJHt92%2bww%3d%3d",
        "\u5b57\u8282\u5927\u5c0f": 163981880,
        "Sha1": "ZWSbImO1EYS4ZMGkcKPD3OpOQ14=",
        "Sha256": "70b8644136ef50b3cc4719f414f628709d93573a363363671c869d923b5df3f8",
        "version": "144.0.3719.92"
    },
    "msedge-stable-win-x64": {
        "\u6587\u4ef6\u540d": "MicrosoftEdge_X64_144.0.3719.92.exe",
        "\u4e0b\u8f7d\u94fe\u63a5": "https://msedge.sb.tlu.dl.delivery.mp.microsoft.com/filestreamingservice/files/fd553f7b-c89a-4da7-bd24-85a214cc91b0?P1=1770167780&P2=404&P3=2&P4=LoCoqWbDRAU1izfhhwkVh%2faOK%2bgb%2fHyqBxHahWpuXhTz8bQWGXfhjWDeGTbMsU8WwP%2fwnRhMsr3oUbXcZN3dhg%3d%3d",
        "\u5b57\u8282\u5927\u5c0f": 185153080,
        "Sha1": "cZuqn8deHCZVuFBXpmqr1LVbcFA=",
        "Sha256": "74d0bbcd2396ac37e89e47e8ce37a598fbb3206abd8bc6fb1f7de24b3fe924cd",
        "version": "144.0.3719.92"
    },
    "msedge-stable-win-ARM64": {
        "\u6587\u4ef6\u540d": "MicrosoftEdge_ARM64_144.0.3719.92.exe",
        "\u4e0b\u8f7d\u94fe\u63a5": "https://msedge.sb.tlu.dl.delivery.mp.microsoft.com/filestreamingservice/files/4b711e81-7521-49da-86e1-b16c44919245?P1=1770167780&P2=404&P3=2&P4=OlKoB4wFcIV1%2fq1z8DlQ1QsPXfhp7ZDe0vOzFZmXZbKYu1IuItBWz7PSEBUnc%2flqhUNFArk%2fGonMv7zWdHxoAA%3d%3d",
        "\u5b57\u8282\u5927\u5c0f": 193217632,
        "Sha1": "kuOuS8rJK0MBdvmxiIT0oqLOYGo=",
        "Sha256": "9361b9d566c12ea74deb47b673d32c905b964a46ec96bc03feabaf36e93b19f6",
        "version": "144.0.3719.92"
    },
    "msedge-beta-win-x86": {
        "\u6587\u4ef6\u540d": "MicrosoftEdge_X86_145.0.3800.22.exe",
        "\u4e0b\u8f7d\u94fe\u63a5": "https://msedge.sb.tlu.dl.delivery.mp.microsoft.com/filestreamingservice/files/ae567afc-0d09-45d8-9b23-5fd3caa84013?P1=1770167781&P2=404&P3=2&P4=JP%2fivGh4nUtb6jqxX%2fOIRF9eSo%2f7XkesOv638vjioAxUanAF0ircJKfcRYNRgKculQodv3bByV8Wuj%2bzTF0kpQ%3d%3d",
        "\u5b57\u8282\u5927\u5c0f": 164717664,
        "Sha1": "ODu1D4LeOFMv962zDRc2IF1YjRo=",
        "Sha256": "70a213633dde8446ac074f609aca0b992730a79e405aece5d2bcc6c945dd2553",
        "version": "145.0.3800.22"
    },
    "msedge-beta-win-x64": {
        "\u6587\u4ef6\u540d": "MicrosoftEdge_X64_145.0.3800.22.exe",
        "\u4e0b\u8f7d\u94fe\u63a5": "https://msedge.sb.tlu.dl.delivery.mp.microsoft.com/filestreamingservice/files/6ddb515a-3dd7-4c4a-8711-cdbdfbf9f6c6?P1=1770167781&P2=404&P3=2&P4=aagzjV3LrRyOO52zn2j0zlEp1pElLpWhOPMsfiL8MJIXKPtQJgiq1D1K3zbv6S5860aerxD1lVnJrN1QkAaoug%3d%3d",
        "\u5b57\u8282\u5927\u5c0f": 185714232,
        "Sha1": "VndPCkD4ZSByhOQ1Qn5jqSG1IQY=",
        "Sha256": "63bc1d3a87697ec5bffa5d627720ef65a834c4e3d7bbbcc69d916134efcd4955",
        "version": "145.0.3800.22"
    },
    "msedge-beta-win-ARM64": {
        "\u6587\u4ef6\u540d": "MicrosoftEdge_ARM64_145.0.3800.22.exe",
        "\u4e0b\u8f7d\u94fe\u63a5": "https://msedge.sb.tlu.dl.delivery.mp.microsoft.com/filestreamingservice/files/29d8b075-4427-401b-95e8-0eb9e78d5289?P1=1770167781&P2=404&P3=2&P4=Ef%2b9Y8rN9L%2bYtKJf1lQVTro2DYTPggU402z6gEJM4DC5xAM4R1ESvsXca%2biNFy51PArFxntrvXY0IYDuWEb8cg%3d%3d",
        "\u5b57\u8282\u5927\u5c0f": 194127968,
        "Sha1": "DHKA76rXZRQZrnpuuVf7bYon8+M=",
        "Sha256": "57d668c52324b0060f46d11191977b03284a9abd58459a1ff6866c6bd09b4e97",
        "version": "145.0.3800.22"
    },
    "msedge-dev-win-x86": {
        "\u6587\u4ef6\u540d": "MicrosoftEdge_X86_146.0.3818.0.exe",
        "\u4e0b\u8f7d\u94fe\u63a5": "https://msedge.sb.tlu.dl.delivery.mp.microsoft.com/filestreamingservice/files/ca7e4710-46c8-4761-bfca-1dde56d40dbb?P1=1770167781&P2=404&P3=2&P4=heov4sL5wDs2AqoL8F0WzOsaLf%2bMX7UtW%2bT%2f5qB82rKYLss75CVrgJmI47XlLqeQu5%2bgQrn5vyFd7AmzRYY88w%3d%3d",
        "\u5b57\u8282\u5927\u5c0f": 164596312,
        "Sha1": "3u6gJUbrqsTaU+TQK3izoXlyy1o=",
        "Sha256": "5f150af42f661ba1f06f9289652130c62077b3b8b3bde06dd97ef754ff6f3e4f",
        "version": "146.0.3818.0"
    },
    "msedge-dev-win-x64": {
        "\u6587\u4ef6\u540d": "MicrosoftEdge_X64_146.0.3818.0.exe",
        "\u4e0b\u8f7d\u94fe\u63a5": "https://msedge.sb.tlu.dl.delivery.mp.microsoft.com/filestreamingservice/files/8191bf5e-7094-4019-bb79-4748d0c7c6ea?P1=1770167781&P2=404&P3=2&P4=NQVYaHtjj1Q2rD0Ab4E0MldTQkmxyrzQnU%2b%2bM963sAyO4YUW%2fY2XT3zfy5SnYAqWycpKQ54J%2bGo3YfZFOkbKrw%3d%3d",
        "\u5b57\u8282\u5927\u5c0f": 185806432,
        "Sha1": "C7OfPJZB7oWeZCP4loncxx3SV6k=",
        "Sha256": "65f38bf47b6540e769ea822db48e7008e24a68bdb8751db0cd540081657d037e",
        "version": "146.0.3818.0"
    },
    "msedge-dev-win-ARM64": {
        "\u6587\u4ef6\u540d": "MicrosoftEdge_ARM64_146.0.3818.0.exe",
        "\u4e0b\u8f7d\u94fe\u63a5": "https://msedge.sb.tlu.dl.delivery.mp.microsoft.com/filestreamingservice/files/ccb2ac4e-9153-4c2f-a714-4f3ab3d00b08?P1=1770167782&P2=404&P3=2&P4=Cg9vuoxItgT1cw%2bdSIBJqD%2fFL4scNG4eDNZiB8iVxdHapPmuUr8np5Tn96wKO84IQE%2f10W4eEV3zNbvNWnyjSQ%3d%3d",
        "\u5b57\u8282\u5927\u5c0f": 194208824,
        "Sha1": "ssvPbrlhGubFoYIbxw7c0sVneMo=",
        "Sha256": "d1a3270372105dc4dc8cc2243ba7c85796a19924c00218a021f795e9e9338216",
        "version": "146.0.3818.0"
    },
    "msedge-canary-win-x86": {
        "\u6587\u4ef6\u540d": "MicrosoftEdge_X86_146.0.3827.0.exe",
        "\u4e0b\u8f7d\u94fe\u63a5": "https://msedge.sb.tlu.dl.delivery.mp.microsoft.com/filestreamingservice/files/9908a3b5-4457-4fef-ab21-872642ff2c7a?P1=1770167782&P2=404&P3=2&P4=lN%2fyWt%2fOm9WsjokhbyiZ9S6nPUmeqhqWRd4mZWzvseZekxj6HirTGxwoQiv%2fk9CX7uBGoI3SFqPMwU8pEHJh9A%3d%3d",
        "\u5b57\u8282\u5927\u5c0f": 165955640,
        "Sha1": "HQEcjOX4TSgHhGGtubz6xZtSVLk=",
        "Sha256": "6af6727a2224d89a858d139a1d0f759f9d050b3f26298f05c63c4eb7f4d02b01",
        "version": "146.0.3827.0"
    },
    "msedge-canary-win-x64": {
        "\u6587\u4ef6\u540d": "MicrosoftEdge_X64_146.0.3827.0.exe",
        "\u4e0b\u8f7d\u94fe\u63a5": "https://msedge.sb.tlu.dl.delivery.mp.microsoft.com/filestreamingservice/files/0e43ae17-93c7-4e16-bf43-84244bbc929e?P1=1770167782&P2=404&P3=2&P4=EYfWEWrJtzsi7QydJc%2b0CF4KDyKWb1h6n5LUHL%2bY7Td%2b%2flDCsd8YvAIXCCu6F6kFJ7i8GYCjdqSKTJGJIdNVRQ%3d%3d",
        "\u5b57\u8282\u5927\u5c0f": 188181560,
        "Sha1": "bRoJJIwi5Is2qcQBPCMShxrb/4c=",
        "Sha256": "351bdb92b44edc32ade55cfc8e07d09c47838105c7e976f7351fc0d06f20c69b",
        "version": "146.0.3827.0"
    },
    "msedge-canary-win-ARM64": {
        "\u6587\u4ef6\u540d": "MicrosoftEdge_ARM64_146.0.3827.0.exe",
        "\u4e0b\u8f7d\u94fe\u63a5": "https://msedge.sb.tlu.dl.delivery.mp.microsoft.com/filestreamingservice/files/39924b77-03f2-401e-b8a0-d9e7a23484c6?P1=1770167782&P2=404&P3=2&P4=OojAUzW63P8C3Z7qs2oDmlcbhFWye2qx7%2f%2b4fReNEHg9awWH4FArT9jBfjoMW%2fBDK%2bXHvJ%2b196ECSy41C%2bDXgg%3d%3d",
        "\u5b57\u8282\u5927\u5c0f": 196007992,
        "Sha1": "DGzThWtxnRCeg1jQnH3fGwu5cgk=",
        "Sha256": "2a3addfba550fa6565fc344f6ed09862a26bc1b6514e2e0954748ff52bfa1ada",
        "version": "146.0.3827.0"
    }
}